{
  "name": "Heart Dimension",
  "$schema": "https://raw.githubusercontent.com/Outer-Wilds-New-Horizons/new-horizons/main/NewHorizons/Schemas/body_schema.json",
  "starSystem": "BrambleSystem",

  "Base": {
    "groundSize": 0,
    "surfaceSize": 0,
    "surfaceGravity": 0,
    "hasMapMarker": false,
    "showMinimap": false
  },
  "Orbit": {
    "staticPosition": {
      "x": -10000,
      "y": 0,
      "z": 0
    }
  },
  "Bramble": {
    "dimension": {
      "linksTo": "Hot Node",
      "fogDensity": 6,
      "radius": 500
    }
  }
}
